sqs_launcher/__init__.py
sqs_listener/__init__.py
sqs_listener/daemon.py
sqs_queue/__init__.py
cloudAgnosticPySqsListener-0.9.4.dist-info/LICENSE
cloudAgnosticPySqsListener-0.9.4.dist-info/METADATA
cloudAgnosticPySqsListener-0.9.4.dist-info/WHEEL
cloudAgnosticPySqsListener-0.9.4.dist-info/top_level.txt
cloudAgnosticPySqsListener-0.9.4.dist-info/RECORD
