Metadata-Version: 2.1
Name: cloudAgnosticPySqsListener
Version: 0.9.4
Summary: A simple cloud agnostic Python SQS utility package
Home-page: https://github.com/phedone/python-sqs-listener
Author: Tom HENEAULT
Author-email: tom@phedone.com
License: Apache Software License
Keywords: aws sqs listener and message launcher
Classifier: Development Status :: 4 - Beta
Classifier: Intended Audience :: Developers
Classifier: Topic :: Software Development :: Libraries
Classifier: License :: OSI Approved :: Apache Software License
Classifier: Programming Language :: Python :: 2.7
Classifier: Programming Language :: Python :: 3.6
License-File: LICENSE
Requires-Dist: boto3
